{"MatchResults":{"playerListHome":[{"player":"Tommy Bäckman (M081256TOM02)","licNbr":"M081256TOM02","homeOrAwayTeam":1,"result1":241,"result2":243,"result3":246,"result4":246,"hcp":0,"totalResultWithoutHcp":976,"totalSeries":4,"lanePoint":3,"laneRankPoints":1.89,"place":1,"totalResult":976,"rankPoints":22.0,"totalPoints":23.89},{"player":"Johan Jerräng (M180379JOH03)","licNbr":"M180379JOH03","homeOrAwayTeam":1,"result1":207,"result2":217,"result3":247,"result4":231,"hcp":0,"totalResultWithoutHcp":902,"totalSeries":4,"lanePoint":2,"laneRankPoints":1.31,"place":3,"totalResult":902,"rankPoints":13.07495,"totalPoints":14.38495},{"player":"Christian Holmberg (M300385CHR01)","licNbr":"M300385CHR01","homeOrAwayTeam":1,"result1":213,"result2":224,"result3":195,"result4":223,"hcp":0,"totalResultWithoutHcp":855,"totalSeries":4,"lanePoint":3,"laneRankPoints":1.71,"place":4,"totalResult":855,"rankPoints":10.73785,"totalPoints":12.44785},{"player":"Johan Eklund (M200168JOH03)","licNbr":"M200168JOH03","homeOrAwayTeam":1,"result1":205,"result2":192,"result3":193,"result4":235,"hcp":0,"totalResultWithoutHcp":825,"totalSeries":4,"lanePoint":3,"laneRankPoints":1.82,"place":7,"totalResult":825,"rankPoints":6.19157,"totalPoints":8.01157},{"player":"Jonathan Havstad (M250582JON09)","licNbr":"M250582JON09","homeOrAwayTeam":1,"result1":185,"result2":205,"result3":193,"result4":203,"hcp":0,"totalResultWithoutHcp":786,"totalSeries":4,"lanePoint":1,"laneRankPoints":0.6,"place":10,"totalResult":786,"rankPoints":3.29397,"totalPoints":3.89397},{"player":"Thomas Hörnberg (M271054THO01)","licNbr":"M271054THO01","homeOrAwayTeam":1,"result1":193,"result2":220,"result3":170,"result4":202,"hcp":0,"totalResultWithoutHcp":785,"totalSeries":4,"lanePoint":3,"laneRankPoints":1.78,"place":11,"totalResult":785,"rankPoints":2.51968,"totalPoints":4.29968},{"player":"Johan Hultgren (M300373JOH01)","licNbr":"M300373JOH01","homeOrAwayTeam":1,"result1":169,"result2":192,"result3":191,"result4":210,"hcp":0,"totalResultWithoutHcp":762,"totalSeries":4,"lanePoint":1,"laneRankPoints":0.6,"place":14,"totalResult":762,"rankPoints":0.56049,"totalPoints":1.16049},{"player":"Kristian Hiltunen (M150481KRI01)","licNbr":"M150481KRI01","homeOrAwayTeam":1,"result1":212,"result2":189,"result3":0,"result4":0,"hcp":0,"totalResultWithoutHcp":401,"totalSeries":2,"lanePoint":2,"laneRankPoints":1.09,"place":15,"totalResult":401,"rankPoints":0.0,"totalPoints":1.09},{"player":"Henrik Johansson (M190381HEN01)","licNbr":"M190381HEN01","homeOrAwayTeam":1,"result1":169,"result2":156,"result3":0,"result4":0,"hcp":0,"totalResultWithoutHcp":325,"totalSeries":2,"lanePoint":0,"laneRankPoints":0.0,"place":18,"totalResult":325,"rankPoints":0.0,"totalPoints":0.0}],"playerListAway":[{"player":"Christer Liedholm (M131061CHR01)","licNbr":"M131061CHR01","homeOrAwayTeam":0,"result1":238,"result2":216,"result3":267,"result4":205,"hcp":0,"totalResultWithoutHcp":926,"totalSeries":4,"lanePoint":3,"laneRankPoints":2.02,"place":2,"totalResult":926,"rankPoints":16.36892,"totalPoints":18.38892},{"player":"Peter Sjöberg (M190348PET01)","licNbr":"M190348PET01","homeOrAwayTeam":0,"result1":210,"result2":210,"result3":223,"result4":195,"hcp":0,"totalResultWithoutHcp":838,"totalSeries":4,"lanePoint":3,"laneRankPoints":1.88,"place":5,"totalResult":838,"rankPoints":8.92505,"totalPoints":10.80505},{"player":"Alf Kindblom (M160553ALF01)","licNbr":"M160553ALF01","homeOrAwayTeam":0,"result1":176,"result2":217,"result3":181,"result4":258,"hcp":0,"totalResultWithoutHcp":832,"totalSeries":4,"lanePoint":1,"laneRankPoints":0.68,"place":6,"totalResult":832,"rankPoints":7.44388,"totalPoints":8.12388},{"player":"Lennart Axelsson (M270844LEN01)","licNbr":"M270844LEN01","homeOrAwayTeam":0,"result1":206,"result2":205,"result3":180,"result4":224,"hcp":0,"totalResultWithoutHcp":815,"totalSeries":4,"lanePoint":3,"laneRankPoints":1.72,"place":8,"totalResult":815,"rankPoints":5.10677,"totalPoints":6.82677},{"player":"Torbjörn Jensen (M100363TOR02)","licNbr":"M100363TOR02","homeOrAwayTeam":0,"result1":192,"result2":232,"result3":213,"result4":157,"hcp":0,"totalResultWithoutHcp":794,"totalSeries":4,"lanePoint":0,"laneRankPoints":0.0,"place":9,"totalResult":794,"rankPoints":4.14991,"totalPoints":4.14991},{"player":"Hans Norbeck (M241152HAN01)","licNbr":"M241152HAN01","homeOrAwayTeam":0,"result1":191,"result2":201,"result3":181,"result4":194,"hcp":0,"totalResultWithoutHcp":767,"totalSeries":4,"lanePoint":1,"laneRankPoints":0.52,"place":12,"totalResult":767,"rankPoints":1.8128,"totalPoints":2.3328},{"player":"Mikael Axelsson (M250277MIK01)","licNbr":"M250277MIK01","homeOrAwayTeam":0,"result1":159,"result2":191,"result3":214,"result4":200,"hcp":0,"totalResultWithoutHcp":764,"totalSeries":4,"lanePoint":3,"laneRankPoints":1.58,"place":13,"totalResult":764,"rankPoints":1.16254,"totalPoints":2.74254},{"player":"Mathias Ernest (M170287MAT08)","licNbr":"M170287MAT08","homeOrAwayTeam":0,"result1":182,"result2":174,"result3":0,"result4":0,"hcp":0,"totalResultWithoutHcp":356,"totalSeries":2,"lanePoint":0,"laneRankPoints":0.0,"place":16,"totalResult":356,"rankPoints":0.0,"totalPoints":0.0},{"player":"Lars Öberg (M310559LAR01)","licNbr":"M310559LAR01","homeOrAwayTeam":0,"result1":160,"result2":191,"result3":0,"result4":0,"hcp":0,"totalResultWithoutHcp":351,"totalSeries":2,"lanePoint":0,"laneRankPoints":0.0,"place":17,"totalResult":351,"rankPoints":0.0,"totalPoints":0.0}]},"MatchScores":{"series":[{"boards":[{"scores":[{"playerName":"J. Havstad","score":185,"laneScore":0,"scoreId":"lblSerie1Table1Order1"},{"playerName":"J. Jerräng","score":207,"laneScore":0,"scoreId":"lblSerie1Table2Order1"},{"playerName":"C. Holmberg","score":213,"laneScore":1,"scoreId":"lblSerie1Table3Order1"},{"playerName":"J. Eklund","score":205,"laneScore":1,"scoreId":"lblSerie1Table4Order1"}],"boardId":null,"boardName":null},{"scores":[{"playerName":"J. Hultgren","score":169,"laneScore":354,"scoreId":"lblSerie1Table1Order2"},{"playerName":"H. Johansson","score":169,"laneScore":376,"scoreId":"lblSerie1Table2Order2"},{"playerName":"T. Bäckman","score":241,"laneScore":454,"scoreId":"lblSerie1Table3Order2"},{"playerName":"T. Hörnberg","score":193,"laneScore":398,"scoreId":"lblSerie1Table4Order2"}],"boardId":null,"boardName":null},{"scores":[{"playerName":"M. Axelsson","score":159,"laneScore":1,"scoreId":"lblSerie1Table1Order3"},{"playerName":"L. Axelsson","score":206,"laneScore":1,"scoreId":"lblSerie1Table2Order3"},{"playerName":"M. Ernest","score":182,"laneScore":0,"scoreId":"lblSerie1Table3Order3"},{"playerName":"A. Kindblom","score":176,"laneScore":0,"scoreId":"lblSerie1Table4Order3"}],"boardId":null,"boardName":null},{"scores":[{"playerName":"C. Liedholm","score":238,"laneScore":397,"scoreId":"lblSerie1Table1Order4"},{"playerName":"P. Sjöberg","score":210,"laneScore":416,"scoreId":"lblSerie1Table2Order4"},{"playerName":"T. Jensen","score":192,"laneScore":374,"scoreId":"lblSerie1Table3Order4"},{"playerName":"H. Norbeck","score":191,"laneScore":367,"scoreId":"lblSerie1Table4Order4"}],"boardId":null,"boardName":null}],"serieId":null,"serieName":null},{"boards":[{"scores":[{"playerName":"C. Holmberg","score":224,"laneScore":1,"scoreId":"lblSerie2Table1Order1"},{"playerName":"J. Eklund","score":192,"laneScore":1,"scoreId":"lblSerie2Table2Order1"},{"playerName":"J. Havstad","score":205,"laneScore":0,"scoreId":"lblSerie2Table3Order1"},{"playerName":"J. Jerräng","score":217,"laneScore":0,"scoreId":"lblSerie2Table4Order1"}],"boardId":null,"boardName":null},{"scores":[{"playerName":"T. Bäckman","score":243,"laneScore":467,"scoreId":"lblSerie2Table1Order2"},{"playerName":"T. Hörnberg","score":220,"laneScore":412,"scoreId":"lblSerie2Table2Order2"},{"playerName":"J. Hultgren","score":192,"laneScore":397,"scoreId":"lblSerie2Table3Order2"},{"playerName":"H. Johansson","score":156,"laneScore":373,"scoreId":"lblSerie2Table4Order2"}],"boardId":null,"boardName":null},{"scores":[{"playerName":"A. Kindblom","score":217,"laneScore":0,"scoreId":"lblSerie2Table1Order3"},{"playerName":"M. Ernest","score":174,"laneScore":0,"scoreId":"lblSerie2Table2Order3"},{"playerName":"L. Axelsson","score":205,"laneScore":1,"scoreId":"lblSerie2Table3Order3"},{"playerName":"M. Axelsson","score":191,"laneScore":1,"scoreId":"lblSerie2Table4Order3"}],"boardId":null,"boardName":null},{"scores":[{"playerName":"H. Norbeck","score":201,"laneScore":418,"scoreId":"lblSerie2Table1Order4"},{"playerName":"T. Jensen","score":232,"laneScore":406,"scoreId":"lblSerie2Table2Order4"},{"playerName":"P. Sjöberg","score":210,"laneScore":415,"scoreId":"lblSerie2Table3Order4"},{"playerName":"C. Liedholm","score":216,"laneScore":407,"scoreId":"lblSerie2Table4Order4"}],"boardId":null,"boardName":null}],"serieId":null,"serieName":null},{"boards":[{"scores":[{"playerName":"J. Eklund","score":193,"laneScore":0,"scoreId":"lblSerie3Table1Order1"},{"playerName":"C. Holmberg","score":195,"laneScore":0,"scoreId":"lblSerie3Table2Order1"},{"playerName":"J. Jerräng","score":247,"laneScore":1,"scoreId":"lblSerie3Table3Order1"},{"playerName":"J. Havstad","score":193,"laneScore":1,"scoreId":"lblSerie3Table4Order1"}],"boardId":null,"boardName":null},{"scores":[{"playerName":"T. Hörnberg","score":170,"laneScore":363,"scoreId":"lblSerie3Table1Order2"},{"playerName":"T. Bäckman","score":246,"laneScore":441,"scoreId":"lblSerie3Table2Order2"},{"playerName":"K. Hiltunen","score":212,"laneScore":459,"scoreId":"lblSerie3Table3Order2"},{"playerName":"J. Hultgren","score":191,"laneScore":384,"scoreId":"lblSerie3Table4Order2"}],"boardId":null,"boardName":null},{"scores":[{"playerName":"L. Axelsson","score":180,"laneScore":1,"scoreId":"lblSerie3Table1Order3"},{"playerName":"M. Axelsson","score":214,"laneScore":1,"scoreId":"lblSerie3Table2Order3"},{"playerName":"A. Kindblom","score":181,"laneScore":0,"scoreId":"lblSerie3Table3Order3"},{"playerName":"L. Öberg","score":160,"laneScore":0,"scoreId":"lblSerie3Table4Order3"}],"boardId":null,"boardName":null},{"scores":[{"playerName":"P. Sjöberg","score":223,"laneScore":403,"scoreId":"lblSerie3Table1Order4"},{"playerName":"C. Liedholm","score":267,"laneScore":481,"scoreId":"lblSerie3Table2Order4"},{"playerName":"H. Norbeck","score":181,"laneScore":362,"scoreId":"lblSerie3Table3Order4"},{"playerName":"T. Jensen","score":213,"laneScore":373,"scoreId":"lblSerie3Table4Order4"}],"boardId":null,"boardName":null}],"serieId":null,"serieName":null},{"boards":[{"scores":[{"playerName":"J. Jerräng","score":231,"laneScore":1,"scoreId":"lblSerie4Table1Order1"},{"playerName":"J. Havstad","score":203,"laneScore":0,"scoreId":"lblSerie4Table2Order1"},{"playerName":"J. Eklund","score":235,"laneScore":1,"scoreId":"lblSerie4Table3Order1"},{"playerName":"C. Holmberg","score":223,"laneScore":1,"scoreId":"lblSerie4Table4Order1"}],"boardId":null,"boardName":null},{"scores":[{"playerName":"K. Hiltunen","score":189,"laneScore":420,"scoreId":"lblSerie4Table1Order2"},{"playerName":"J. Hultgren","score":210,"laneScore":413,"scoreId":"lblSerie4Table2Order2"},{"playerName":"T. Hörnberg","score":202,"laneScore":437,"scoreId":"lblSerie4Table3Order2"},{"playerName":"T. Bäckman","score":246,"laneScore":469,"scoreId":"lblSerie4Table4Order2"}],"boardId":null,"boardName":null},{"scores":[{"playerName":"L. Öberg","score":191,"laneScore":0,"scoreId":"lblSerie4Table1Order3"},{"playerName":"A. Kindblom","score":258,"laneScore":1,"scoreId":"lblSerie4Table2Order3"},{"playerName":"M. Axelsson","score":200,"laneScore":0,"scoreId":"lblSerie4Table3Order3"},{"playerName":"L. Axelsson","score":224,"laneScore":0,"scoreId":"lblSerie4Table4Order3"}],"boardId":null,"boardName":null},{"scores":[{"playerName":"T. Jensen","score":157,"laneScore":348,"scoreId":"lblSerie4Table1Order4"},{"playerName":"H. Norbeck","score":194,"laneScore":452,"scoreId":"lblSerie4Table2Order4"},{"playerName":"C. Liedholm","score":205,"laneScore":405,"scoreId":"lblSerie4Table3Order4"},{"playerName":"P. Sjöberg","score":195,"laneScore":419,"scoreId":"lblSerie4Table4Order4"}],"boardId":null,"boardName":null}],"serieId":null,"serieName":null}],"serieNames":[1,2,3,4],"boardNames":["Bord 1              ","Bord 2              ","Bord 3              ","Bord 4              "],"scoreKvpList":{"lblSerie1Table1Order1":{"playerName":"J. Havstad","score":185,"laneScore":0,"scoreId":"lblSerie1Table1Order1"},"lblSerie1Table2Order1":{"playerName":"J. Jerräng","score":207,"laneScore":0,"scoreId":"lblSerie1Table2Order1"},"lblSerie1Table3Order1":{"playerName":"C. Holmberg","score":213,"laneScore":1,"scoreId":"lblSerie1Table3Order1"},"lblSerie1Table4Order1":{"playerName":"J. Eklund","score":205,"laneScore":1,"scoreId":"lblSerie1Table4Order1"},"lblSerie1Table1Order2":{"playerName":"J. Hultgren","score":169,"laneScore":354,"scoreId":"lblSerie1Table1Order2"},"lblSerie1Table2Order2":{"playerName":"H. Johansson","score":169,"laneScore":376,"scoreId":"lblSerie1Table2Order2"},"lblSerie1Table3Order2":{"playerName":"T. Bäckman","score":241,"laneScore":454,"scoreId":"lblSerie1Table3Order2"},"lblSerie1Table4Order2":{"playerName":"T. Hörnberg","score":193,"laneScore":398,"scoreId":"lblSerie1Table4Order2"},"lblSerie1Table1Order3":{"playerName":"M. Axelsson","score":159,"laneScore":1,"scoreId":"lblSerie1Table1Order3"},"lblSerie1Table2Order3":{"playerName":"L. Axelsson","score":206,"laneScore":1,"scoreId":"lblSerie1Table2Order3"},"lblSerie1Table3Order3":{"playerName":"M. Ernest","score":182,"laneScore":0,"scoreId":"lblSerie1Table3Order3"},"lblSerie1Table4Order3":{"playerName":"A. Kindblom","score":176,"laneScore":0,"scoreId":"lblSerie1Table4Order3"},"lblSerie1Table1Order4":{"playerName":"C. Liedholm","score":238,"laneScore":397,"scoreId":"lblSerie1Table1Order4"},"lblSerie1Table2Order4":{"playerName":"P. Sjöberg","score":210,"laneScore":416,"scoreId":"lblSerie1Table2Order4"},"lblSerie1Table3Order4":{"playerName":"T. Jensen","score":192,"laneScore":374,"scoreId":"lblSerie1Table3Order4"},"lblSerie1Table4Order4":{"playerName":"H. Norbeck","score":191,"laneScore":367,"scoreId":"lblSerie1Table4Order4"},"lblSerie2Table1Order1":{"playerName":"C. Holmberg","score":224,"laneScore":1,"scoreId":"lblSerie2Table1Order1"},"lblSerie2Table2Order1":{"playerName":"J. Eklund","score":192,"laneScore":1,"scoreId":"lblSerie2Table2Order1"},"lblSerie2Table3Order1":{"playerName":"J. Havstad","score":205,"laneScore":0,"scoreId":"lblSerie2Table3Order1"},"lblSerie2Table4Order1":{"playerName":"J. Jerräng","score":217,"laneScore":0,"scoreId":"lblSerie2Table4Order1"},"lblSerie2Table1Order2":{"playerName":"T. Bäckman","score":243,"laneScore":467,"scoreId":"lblSerie2Table1Order2"},"lblSerie2Table2Order2":{"playerName":"T. Hörnberg","score":220,"laneScore":412,"scoreId":"lblSerie2Table2Order2"},"lblSerie2Table3Order2":{"playerName":"J. Hultgren","score":192,"laneScore":397,"scoreId":"lblSerie2Table3Order2"},"lblSerie2Table4Order2":{"playerName":"H. Johansson","score":156,"laneScore":373,"scoreId":"lblSerie2Table4Order2"},"lblSerie2Table1Order3":{"playerName":"A. Kindblom","score":217,"laneScore":0,"scoreId":"lblSerie2Table1Order3"},"lblSerie2Table2Order3":{"playerName":"M. Ernest","score":174,"laneScore":0,"scoreId":"lblSerie2Table2Order3"},"lblSerie2Table3Order3":{"playerName":"L. Axelsson","score":205,"laneScore":1,"scoreId":"lblSerie2Table3Order3"},"lblSerie2Table4Order3":{"playerName":"M. Axelsson","score":191,"laneScore":1,"scoreId":"lblSerie2Table4Order3"},"lblSerie2Table1Order4":{"playerName":"H. Norbeck","score":201,"laneScore":418,"scoreId":"lblSerie2Table1Order4"},"lblSerie2Table2Order4":{"playerName":"T. Jensen","score":232,"laneScore":406,"scoreId":"lblSerie2Table2Order4"},"lblSerie2Table3Order4":{"playerName":"P. Sjöberg","score":210,"laneScore":415,"scoreId":"lblSerie2Table3Order4"},"lblSerie2Table4Order4":{"playerName":"C. Liedholm","score":216,"laneScore":407,"scoreId":"lblSerie2Table4Order4"},"lblSerie3Table1Order1":{"playerName":"J. Eklund","score":193,"laneScore":0,"scoreId":"lblSerie3Table1Order1"},"lblSerie3Table2Order1":{"playerName":"C. Holmberg","score":195,"laneScore":0,"scoreId":"lblSerie3Table2Order1"},"lblSerie3Table3Order1":{"playerName":"J. Jerräng","score":247,"laneScore":1,"scoreId":"lblSerie3Table3Order1"},"lblSerie3Table4Order1":{"playerName":"J. Havstad","score":193,"laneScore":1,"scoreId":"lblSerie3Table4Order1"},"lblSerie3Table1Order2":{"playerName":"T. Hörnberg","score":170,"laneScore":363,"scoreId":"lblSerie3Table1Order2"},"lblSerie3Table2Order2":{"playerName":"T. Bäckman","score":246,"laneScore":441,"scoreId":"lblSerie3Table2Order2"},"lblSerie3Table3Order2":{"playerName":"K. Hiltunen","score":212,"laneScore":459,"scoreId":"lblSerie3Table3Order2"},"lblSerie3Table4Order2":{"playerName":"J. Hultgren","score":191,"laneScore":384,"scoreId":"lblSerie3Table4Order2"},"lblSerie3Table1Order3":{"playerName":"L. Axelsson","score":180,"laneScore":1,"scoreId":"lblSerie3Table1Order3"},"lblSerie3Table2Order3":{"playerName":"M. Axelsson","score":214,"laneScore":1,"scoreId":"lblSerie3Table2Order3"},"lblSerie3Table3Order3":{"playerName":"A. Kindblom","score":181,"laneScore":0,"scoreId":"lblSerie3Table3Order3"},"lblSerie3Table4Order3":{"playerName":"L. Öberg","score":160,"laneScore":0,"scoreId":"lblSerie3Table4Order3"},"lblSerie3Table1Order4":{"playerName":"P. Sjöberg","score":223,"laneScore":403,"scoreId":"lblSerie3Table1Order4"},"lblSerie3Table2Order4":{"playerName":"C. Liedholm","score":267,"laneScore":481,"scoreId":"lblSerie3Table2Order4"},"lblSerie3Table3Order4":{"playerName":"H. Norbeck","score":181,"laneScore":362,"scoreId":"lblSerie3Table3Order4"},"lblSerie3Table4Order4":{"playerName":"T. Jensen","score":213,"laneScore":373,"scoreId":"lblSerie3Table4Order4"},"lblSerie4Table1Order1":{"playerName":"J. Jerräng","score":231,"laneScore":1,"scoreId":"lblSerie4Table1Order1"},"lblSerie4Table2Order1":{"playerName":"J. Havstad","score":203,"laneScore":0,"scoreId":"lblSerie4Table2Order1"},"lblSerie4Table3Order1":{"playerName":"J. Eklund","score":235,"laneScore":1,"scoreId":"lblSerie4Table3Order1"},"lblSerie4Table4Order1":{"playerName":"C. Holmberg","score":223,"laneScore":1,"scoreId":"lblSerie4Table4Order1"},"lblSerie4Table1Order2":{"playerName":"K. Hiltunen","score":189,"laneScore":420,"scoreId":"lblSerie4Table1Order2"},"lblSerie4Table2Order2":{"playerName":"J. Hultgren","score":210,"laneScore":413,"scoreId":"lblSerie4Table2Order2"},"lblSerie4Table3Order2":{"playerName":"T. Hörnberg","score":202,"laneScore":437,"scoreId":"lblSerie4Table3Order2"},"lblSerie4Table4Order2":{"playerName":"T. Bäckman","score":246,"laneScore":469,"scoreId":"lblSerie4Table4Order2"},"lblSerie4Table1Order3":{"playerName":"L. Öberg","score":191,"laneScore":0,"scoreId":"lblSerie4Table1Order3"},"lblSerie4Table2Order3":{"playerName":"A. Kindblom","score":258,"laneScore":1,"scoreId":"lblSerie4Table2Order3"},"lblSerie4Table3Order3":{"playerName":"M. Axelsson","score":200,"laneScore":0,"scoreId":"lblSerie4Table3Order3"},"lblSerie4Table4Order3":{"playerName":"L. Axelsson","score":224,"laneScore":0,"scoreId":"lblSerie4Table4Order3"},"lblSerie4Table1Order4":{"playerName":"T. Jensen","score":157,"laneScore":348,"scoreId":"lblSerie4Table1Order4"},"lblSerie4Table2Order4":{"playerName":"H. Norbeck","score":194,"laneScore":452,"scoreId":"lblSerie4Table2Order4"},"lblSerie4Table3Order4":{"playerName":"C. Liedholm","score":205,"laneScore":405,"scoreId":"lblSerie4Table3Order4"},"lblSerie4Table4Order4":{"playerName":"P. Sjöberg","score":195,"laneScore":419,"scoreId":"lblSerie4Table4Order4"}},"boardColSpan":3},"HeadResultInfo":{"matchHeadHomeTeamResult":0,"matchHeadAwayTeamResult":0,"matchHeadHomeTotalScore":6617,"matchHeadAwayTotalScore":6443,"matchHeadHomeTotalRp":13,"matchHeadAwayTotalRp":7,"homeHeadDetails":[{"squadId":1,"teamScore":1582,"teamRP":3},{"squadId":2,"teamScore":1649,"teamRP":3},{"squadId":3,"teamScore":1647,"teamRP":3},{"squadId":4,"teamScore":1739,"teamRP":4}],"awayHeadDetails":[{"squadId":1,"teamScore":1554,"teamRP":2},{"squadId":2,"teamScore":1646,"teamRP":2},{"squadId":3,"teamScore":1619,"teamRP":2},{"squadId":4,"teamScore":1624,"teamRP":1}],"matchHeadHomeTeamScoreRound1":0,"matchHeadHomeTeamScoreRound2":0,"matchHeadHomeTeamScoreRound3":0,"matchHeadHomeTeamScoreRound4":0,"matchHeadHomeTeamRankPointRound1":0.0,"matchHeadHomeTeamRankPointRound2":0.0,"matchHeadHomeTeamRankPointRound3":0.0,"matchHeadHomeTeamRankPointRound4":0.0,"matchHeadAwayTeamScoreRound1":0,"matchHeadAwayTeamScoreRound2":0,"matchHeadAwayTeamScoreRound3":0,"matchHeadAwayTeamScoreRound4":0,"matchHeadAwayTeamRankPointRound1":0.0,"matchHeadAwayTeamRankPointRound2":0.0,"matchHeadAwayTeamRankPointRound3":0.0,"matchHeadAwayTeamRankPointRound4":0.0,"matchHeadHomeTeamScore":0,"matchHeadAwayTeamScore":0,"matchHeadHomeTeamRankPoints":0.0,"matchHeadAwayTeamRankPoints":0.0},"HeadInfo":{"dayOfWeek":"Lör","divisionIsCup":false,"matchId":3050651,"standingsURL":null,"matchFactURL":null,"hallSchemeURL":null,"matchTeamHomeVsAway":null,"matchDateTime":null,"matchEndDateTime":"0001-01-01T00:00:00","matchIdPrevious":0,"matchLotTemplateRowRoundNbr":0,"matchStatus":3,"matchHomeTeamId":181928,"matchHomeClubId":40732,"matchAwayClubId":1660,"matchHomeTeamTypeType":null,"matchAwayTeamTypeType":null,"matchHomeTeamName":"NBC Gullmarsplan BC","matchHomeTeamAlias":"NBC Gullmarsplan BC A","matchAwayTeamId":90478,"matchAwayTeamName":"Fredrikshof IF","matchAwayTeamAlias":"Fredrikshof IF A","matchAlleyGroup":2,"alleyGroupName":null,"alleyGroupStartLane":0,"alleyGroupNbrOfLanes":0,"rankCompetition":0.0,"matchDate":"2014-01-18T00:00:00","matchDivisionId":8,"divisionRegion":2,"matchLeagueId":1,"matchLevelId":3,"matchDivisionHcp":0,"matchDivisionName":"Div 1 Södra Svealand","matchDivisionShortName":null,"matchHallId":777,"matchHallName":"Stockholm - Gullmarsplan","matchRoundId":11,"matchNbrOfLanes":8,"matchNbrOfPlayers":8,"matchSchemeId":"8M8BA","matchFinished":true,"matchTime":1000,"matchEndTime":0,"levelPlayTime":0,"matchTimeOld":0,"matchDateOld":"1900-01-01T00:00:00","matchHcp":0,"matchBossGroup":0,"matchLanePoints":true,"matchHomeTeamScore":6617,"matchAwayTeamScore":6443,"matchHomeTeamResult":13,"matchAwayTeamResult":7,"matchSeason":2013,"licenceAgreementSeason":0,"clubAgreementSeason":0,"teamLevel":0,"matchOmit":false,"hallIdSbhf":0,"matchAllot":false,"matchLotExtraMatch":false,"matchStrikeOut":false,"matchStrikeOutNbrOfRounds":0,"matchCompetitionLevel":0.0,"matchStrikeOutBool":false,"matchDateTimeChanged":false,"matchHomeTeamVsAwayTeam":"NBC Gullmarsplan BC - Fredrikshof IF","matchResult":"13 - 7","matchTeams":"NBC Gullmarsplan BC A - Fredrikshof IF A ","homeTeamStartLane":0,"homeTeamNbrOfLanes":0,"homeTeamLaneGroup":"","matchHour":0,"matchMinute":0,"matchDayFormatted":"lördag 18 januari ","matchDayFormattedWithRound":"Lör 18/1, Omg.11","matchDayFormattedReportDates":"lördag 18 januari ","regionName":"Svealand","matchTimeFormatted":"10:00","matchTimeOldFormatted":"","matchRoundFormatted":"Omgång 11","matchAwayTeamHallAndTime":"Stockholm - Gullmarsplan;lördag 18 januari  10:00","matchRowNbr":0,"matchOilPatternId":0,"oilPatterns":[],"matchOilPatternName":"Ingen OljeProfil","matchFinishedHomeTeam":false,"matchFinishedAwayTeam":false,"matchReportStartDate":"0001-01-01T00:00:00","matchReportEndDate":"0001-01-01T00:00:00","cupId":0,"cupRoundId":0,"cupCellNbr":0,"cupNbrOfMatches":0,"lotTemplateIncludeMatchFromPreviousRound":false,"divisionSeasonStartMatchDayNo":0}}